scrapbook/__init__.py
scrapbook/api.py
scrapbook/exceptions.py
scrapbook/log.py
scrapbook/models.py
scrapbook/translators.py
scrapbook/version.py
scrapbook_beta-0.1.0.dist-info/LICENSE
scrapbook_beta-0.1.0.dist-info/METADATA
scrapbook_beta-0.1.0.dist-info/WHEEL
scrapbook_beta-0.1.0.dist-info/top_level.txt
scrapbook_beta-0.1.0.dist-info/RECORD
